{
        "/api": "api docs",
        "/api/signup": "signup",
        "/api/signin": "signin",
        "/api/signout": "signout",
        "/api/users": "get all users",
        "/api/user/:userId": "get/update/delete user",
        "/api/user/bgg/:bggUsername&:userId": "update bggUsername",
        "/api/user/follow": "follow user",
        "/api/user/unfollow": "unfollow user",
        "/api/user/photo/:userId": "get user photos",
        "/api/user/findpeople/:userId": "return list of users not including followers and self",
        "/api/posts": "get all posts",
        "/api/post/new/:userId": "create new post",
        "/api/posts/by/:userId": "get posts by user",
        "/api/post/:postId": "update/delete post"
}
